setup.py
musicbox.egg-info/PKG-INFO
musicbox.egg-info/SOURCES.txt
musicbox.egg-info/dependency_links.txt
musicbox.egg-info/entry_points.txt
musicbox.egg-info/not-zip-safe
musicbox.egg-info/requires.txt
musicbox.egg-info/top_level.txt
src/__init__.py
src/api.py
src/const.py
src/logger.py
src/menu.py
src/player.py
src/ui.py