Metadata-Version: 1.0
Name: musicbox
Version: 0.1.2.4
Summary: A sexy command line interface musicbox
Home-page: https://github.com/darknessomi/musicbox
Author: omi
Author-email: 4399.omi@gmail.com
License: UNKNOWN
Keywords: music,netease,cli,player
Platform: UNKNOWN
